elfobs/__init__.py
elfobs/cli.py
elfobs/display.py
elfobs/fonts/NotoSerif-Black.ttf
elfobs/fonts/NotoSerif-BlackItalic.ttf
elfobs/fonts/NotoSerif-Bold.ttf
elfobs/fonts/NotoSerif-BoldItalic.ttf
elfobs/fonts/NotoSerif-Italic.ttf
elfobs/fonts/NotoSerif-Light.ttf
elfobs/fonts/NotoSerif-LightItalic.ttf
elfobs/fonts/NotoSerif-Medium.ttf
elfobs/fonts/NotoSerif-MediumItalic.ttf
elfobs/fonts/NotoSerif-Regular.ttf
elfobs/fonts/NotoSerif-Thin.ttf
elfobs/fonts/NotoSerif-ThinItalic.ttf
elfobs/fonts/__init__.py
elfobs/image.py
elfobs/obs.py
elfobs/sched.py
elfobs/sound.py
elfobs/video.py
elfobs-0.1.4.dist-info/METADATA
elfobs-0.1.4.dist-info/WHEEL
elfobs-0.1.4.dist-info/entry_points.txt
elfobs-0.1.4.dist-info/RECORD
