Metadata-Version: 2.1
Name: elfobs
Version: 0.1.4
Summary: 
Author: Aldo A. Villagra B.
Author-email: aldovillagra@gmail.com
Requires-Python: >=3.9,<4.0
Classifier: Programming Language :: Python :: 3
Classifier: Programming Language :: Python :: 3.9
Classifier: Programming Language :: Python :: 3.10
Classifier: Programming Language :: Python :: 3.11
Classifier: Programming Language :: Python :: 3.12
Requires-Dist: obsws-python (>=1.6.1,<2.0.0)
Requires-Dist: omegaconf (>=2.3.0,<3.0.0)
Requires-Dist: pandas[all] (>=2.2.2,<3.0.0)
Requires-Dist: pendulum (>=2.1.2,<3.0.0)
Requires-Dist: pillow (>=10.3.0,<11.0.0)
Requires-Dist: pyalsaaudio (>=0.10.0,<0.11.0)
Requires-Dist: typer[all] (>=0.9.0,<0.10.0)
Requires-Dist: v4l2py (>=2.1.0,<3.0.0)
